rtl/single_line_cache.v
module single_line_cache #(
    parameter ADDR_WIDTH = 32,
    parameter LINE_BYTES = 4
)(
    input  wire                    clk,
    input  wire                    rst_n,
    input  wire [ADDR_WIDTH-1:0]   addr,
    input  wire                    write_enable,
    input  wire [8*LINE_BYTES-1:0] write_data,
    output wire [8*LINE_BYTES-1:0] read_data,
    output wire                    hit
);

    localparam OFFSET_BITS = $clog2(LINE_BYTES);
    localparam TAG_BITS    = ADDR_WIDTH - OFFSET_BITS;

    wire [TAG_BITS-1:0] addr_tag = addr[ADDR_WIDTH-1:OFFSET_BITS];

    reg                    valid;
    reg [TAG_BITS-1:0]     stored_tag;
    reg [8*LINE_BYTES-1:0] stored_data;

    assign hit       = valid && (stored_tag == addr_tag);
    assign read_data = stored_data;

    always @(posedge clk or negedge rst_n) begin
        if (!rst_n) begin
            valid       <= 1'b0;
            stored_tag  <= {TAG_BITS{1'b0}};
            stored_data <= {8*LINE_BYTES{1'b0}};
        end else if (write_enable) begin
            valid       <= 1'b1;
            stored_tag  <= addr_tag;
            stored_data <= write_data;
        end
    end

endmodule

tb/tb_single_line_cache.v
`timescale 1ns / 1ps

module tb_single_line_cache;

    parameter ADDR_WIDTH = 32;
    parameter LINE_BYTES = 4;

    reg                       clk;
    reg                       rst_n;
    reg  [ADDR_WIDTH-1:0]     addr;
    reg                       write_enable;
    reg  [8*LINE_BYTES-1:0]   write_data;
    wire [8*LINE_BYTES-1:0]   read_data;
    wire                      hit;

    integer errors = 0;

    // DUT instantiation
    single_line_cache #(
        .ADDR_WIDTH(ADDR_WIDTH),
        .LINE_BYTES(LINE_BYTES)
    ) dut (
        .clk          (clk),
        .rst_n        (rst_n),
        .addr         (addr),
        .write_enable (write_enable),
        .write_data   (write_data),
        .read_data    (read_data),
        .hit          (hit)
    );

    // Clock: 10ns period
    always #5 clk = ~clk;

    // Self-checking task: compares actual vs. predicted, logs pass/fail
    task check_hit(input expected_hit, input [255:0] label);
        begin
            if (hit !== expected_hit) begin
                $display("FAIL [%s] at t=%0t: hit=%b, expected=%b",
                          label, $time, hit, expected_hit);
                errors = errors + 1;
            end else begin
                $display("PASS [%s] at t=%0t: hit=%b as predicted",
                          label, $time, hit);
            end
        end
    endtask

    task check_data(input [8*LINE_BYTES-1:0] expected_data, input [255:0] label);
        begin
            if (read_data !== expected_data) begin
                $display("FAIL [%s] at t=%0t: read_data=%h, expected=%h",
                          label, $time, read_data, expected_data);
                errors = errors + 1;
            end else begin
                $display("PASS [%s] at t=%0t: read_data=%h as predicted",
                          label, $time, read_data);
            end
        end
    endtask

    initial begin
        $dumpfile("tb_single_line_cache.vcd");
        $dumpvars(0, tb_single_line_cache);

        // ---- Init ----
        clk          = 0;
        rst_n        = 0;
        addr         = 0;
        write_enable = 0;
        write_data   = 0;

        // ---- Step 1: Reset ----
        // Predicted: valid=0 internally, so hit must be 0 regardless of addr.
        @(negedge clk);
        rst_n = 1;
        addr  = 32'h100;
        @(negedge clk);
        check_hit(1'b0, "after reset, before any write");

        // ---- Step 2: Write to 0x100 ----
        // Predicted: next cycle, tag for 0x100 is stored, valid=1.
        addr         = 32'h100;
        write_enable = 1;
        write_data   = 32'hDEADBEEF;
        @(negedge clk);
        write_enable = 0;

        // ---- Step 3: Read 0x100 ----
        // Predicted: same tag as what's stored -> hit=1, data=0xDEADBEEF.
        addr = 32'h100;
        #1; // let combinational hit/read_data settle before checking
        check_hit(1'b1, "read 0x100 after writing 0x100");
        check_data(32'hDEADBEEF, "read 0x100 after writing 0x100");

        // ---- Step 4: Read 0x104 ----
        // Predicted: 0x104 >> 2 != 0x100 >> 2 (different tag, since
        // LINE_BYTES=4 means each word is its own line) -> hit=0.
        @(negedge clk);
        addr = 32'h104;
        #1;
        check_hit(1'b0, "read 0x104, different tag from 0x100");

        // ---- Step 5: Write to 0x200 (evicts 0x100's line) ----
        // Predicted: line now holds 0x200's tag; 0x100 no longer hits.
        @(negedge clk);
        addr         = 32'h200;
        write_enable = 1;
        write_data   = 32'hCAFEF00D;
        @(negedge clk);
        write_enable = 0;

        // ---- Step 6: Read 0x200 ----
        // Predicted: hit=1, data=0xCAFEF00D.
        addr = 32'h200;
        #1;
        check_hit(1'b1, "read 0x200 after eviction write");
        check_data(32'hCAFEF00D, "read 0x200 after eviction write");

        // ---- Step 7: Read 0x100 again ----
        // Predicted: line was evicted by the 0x200 write -> hit=0.
        @(negedge clk);
        addr = 32'h100;
        #1;
        check_hit(1'b0, "read 0x100, should be evicted by 0x200 write");

        // ---- Summary ----
        if (errors == 0)
            $display("\n=== ALL TESTS PASSED ===");
        else
            $display("\n=== %0d TEST(S) FAILED ===", errors);

        $finish;
    end

endmodule

tb_single_line_cache.vcd
$version Generated by VerilatedVcd $end
$timescale 1ps $end
 $scope module tb_single_line_cache $end
  $var wire 32 - ADDR_WIDTH [31:0] $end
  $var wire 32 . LINE_BYTES [31:0] $end
  $var wire 1 * clk $end
  $var wire 1 " rst_n $end
  $var wire 32 # addr [31:0] $end
  $var wire 1 $ write_enable $end
  $var wire 32 % write_data [31:0] $end
  $var wire 32 ' read_data [31:0] $end
  $var wire 1 + hit $end
  $var wire 32 , errors [31:0] $end
  $scope module dut $end
   $var wire 32 - ADDR_WIDTH [31:0] $end
   $var wire 32 . LINE_BYTES [31:0] $end
   $var wire 1 * clk $end
   $var wire 1 " rst_n $end
   $var wire 32 # addr [31:0] $end
   $var wire 1 $ write_enable $end
   $var wire 32 % write_data [31:0] $end
   $var wire 32 ' read_data [31:0] $end
   $var wire 1 + hit $end
   $var wire 32 / OFFSET_BITS [31:0] $end
   $var wire 32 0 TAG_BITS [31:0] $end
   $var wire 30 & addr_tag [29:0] $end
   $var wire 1 ( valid $end
   $var wire 30 ) stored_tag [29:0] $end
   $var wire 32 ' stored_data [31:0] $end
  $upscope $end
 $upscope $end
$enddefinitions $end


#0
0"
b00000000000000000000000000000000 #
0$
b00000000000000000000000000000000 %
b000000000000000000000000000000 &
b00000000000000000000000000000000 '
0(
b000000000000000000000000000000 )
0*
0+
b00000000000000000000000000000000 ,
b00000000000000000000000000100000 -
b00000000000000000000000000000100 .
b00000000000000000000000000000010 /
b00000000000000000000000000011110 0
#5000
1*
#10000
1"
b00000000000000000000000100000000 #
b000000000000000000000001000000 &
0*
#15000
1*
#20000
1$
b11011110101011011011111011101111 %
0*
#25000
b11011110101011011011111011101111 '
1(
b000000000000000000000001000000 )
1*
1+
#30000
0$
0*
#35000
1*
#40000
b00000000000000000000000100000100 #
b000000000000000000000001000001 &
0*
0+
#45000
1*
#50000
b00000000000000000000001000000000 #
1$
b11001010111111101111000000001101 %
b000000000000000000000010000000 &
0*
#55000
b11001010111111101111000000001101 '
b000000000000000000000010000000 )
1*
1+
#60000
0$
0*
#65000
1*
#70000
b00000000000000000000000100000000 #
b000000000000000000000001000000 &
0*
0+
